quetzal_annotator/__init__.py
quetzal_annotator/common_mass_deltas.py
quetzal_annotator/mass_reference.py
quetzal_annotator/ontology.py
quetzal_annotator/ontology_collection.py
quetzal_annotator/ontology_term.py
quetzal_annotator/peptidoform.py
quetzal_annotator/proforma_peptidoform.py
quetzal_annotator/psi-mod.json
quetzal_annotator/psi-ms.json
quetzal_annotator/response.py
quetzal_annotator/spectrum.py
quetzal_annotator/spectrum_annotator.py
quetzal_annotator/spectrum_annotator_helper.py
quetzal_annotator/spectrum_comparator.py
quetzal_annotator/spectrum_examiner.py
quetzal_annotator/spectrum_fetcher.py
quetzal_annotator/unimod.json
quetzal_annotator/universal_spectrum_identifier.py
quetzal_annotator/universal_spectrum_identifier_validator.py
quetzal_annotator/obsolete/spectrum_annotator - Copy.py
quetzal_annotator/obsolete/zztmp/mass_reference-new.py
quetzal_annotator/obsolete/zztmp/spectrum_annotator.py
quetzal_annotator-0.2.0.dist-info/licenses/LICENSE
quetzal_annotator-0.2.0.dist-info/METADATA
quetzal_annotator-0.2.0.dist-info/WHEEL
quetzal_annotator-0.2.0.dist-info/top_level.txt
quetzal_annotator-0.2.0.dist-info/RECORD
