Metadata-Version: 2.4
Name: quetzal_annotator
Version: 0.2.0
Summary: A peptide spectrum fragment ion annotation tool using the PSI mzPAF standard
Author-email: Eric Deutsch <edeutsch@systemsbiology.org>
License-Expression: Apache-2.0
Project-URL: Homepage, https://github.com/Quetzal-Annotator/quetzal-annotator
Project-URL: Issues, https://github.com/Quetzal-Annotator/quetzal-annotator/issues
Keywords: proteomics,mass-spectrometry,peptide,annotation,mzPAF,PSI
Classifier: Development Status :: 4 - Beta
Classifier: Intended Audience :: Science/Research
Classifier: Topic :: Scientific/Engineering :: Bio-Informatics
Classifier: Topic :: Scientific/Engineering :: Chemistry
Classifier: Programming Language :: Python :: 3
Classifier: Operating System :: OS Independent
Requires-Python: >=3.8
License-File: LICENSE
Requires-Dist: numpy
Requires-Dist: requests
Requires-Dist: requests_cache
Requires-Dist: pandas
Requires-Dist: scipy
Requires-Dist: matplotlib
Dynamic: license-file
